simio/__init__.py
simio/buffer.py
simio/net/__init__.py
simio/net/tcp/__init__.py
simio/net/tcp/server.py
simio/net/tcp/stream.py
simio/net/utils.py
simio/py.typed
simio/stream/__init__.py
simio/stream/stream.py
simio/stream/utils.py
simio-1.0.0.dist-info/METADATA
simio-1.0.0.dist-info/WHEEL
simio-1.0.0.dist-info/licenses/LICENSE
simio-1.0.0.dist-info/RECORD
