Metadata-Version: 2.4
Name: simio
Version: 1.0.0
Summary: Simple zero-dependency asynchronous IO
License-Expression: Unlicense
License-File: LICENSE
Keywords: async,io,networking,streams,simio
Author: Dmitry Pershin
Author-email: dapper1291@gmail.com
Requires-Python: >=3.12
Classifier: Development Status :: 5 - Production/Stable
Classifier: Intended Audience :: Developers
Classifier: Natural Language :: English
Classifier: License :: Public Domain
Classifier: Operating System :: OS Independent
Classifier: Topic :: Software Development :: Libraries
Classifier: Topic :: Utilities
Classifier: Programming Language :: Python
Classifier: Programming Language :: Python :: 3.12
Classifier: Programming Language :: Python :: 3.13
Classifier: Programming Language :: Python :: 3.14
Classifier: Typing :: Typed
Project-URL: Documentation, https://github.com/dapper91/simio
Project-URL: Homepage, https://github.com/dapper91/simio
Project-URL: Repository, https://github.com/dapper91/simio
